odoo/addons/l10n_es_dua/README.rst
odoo/addons/l10n_es_dua/__init__.py
odoo/addons/l10n_es_dua/__manifest__.py
odoo/addons/l10n_es_dua/data/fiscal_position_taxes_dua.xml
odoo/addons/l10n_es_dua/data/fiscal_positions_dua.xml
odoo/addons/l10n_es_dua/data/products_dua.xml
odoo/addons/l10n_es_dua/data/tax_group_data.xml
odoo/addons/l10n_es_dua/data/taxes_dua.xml
odoo/addons/l10n_es_dua/i18n/es.po
odoo/addons/l10n_es_dua/i18n/l10n_es_dua.pot
odoo/addons/l10n_es_dua/readme/CONFIGURE.rst
odoo/addons/l10n_es_dua/readme/CONTRIBUTORS.rst
odoo/addons/l10n_es_dua/readme/DESCRIPTION.rst
odoo/addons/l10n_es_dua/readme/USAGE.rst
odoo/addons/l10n_es_dua/static/description/icon.png
odoo/addons/l10n_es_dua/static/description/index.html
odoo13_addon_l10n_es_dua-13.0.1.1.0.dist-info/METADATA
odoo13_addon_l10n_es_dua-13.0.1.1.0.dist-info/WHEEL
odoo13_addon_l10n_es_dua-13.0.1.1.0.dist-info/top_level.txt
odoo13_addon_l10n_es_dua-13.0.1.1.0.dist-info/RECORD
